[
    {
        "name": "rice cake",
        "like": 7,
        "ings": [
            {
                "name": "green onion",
                "quantity": 500,
                "quantity_unit": "g"
            },
            {
                "name": "pepper",
                "quantity": 700,
                "quantity_unit": "kg"
            },
            {
                "name": "water",
                "quantity": 500,
                "quantity_unit": "ml"
            },
            {
                "name": "water2",
                "quantity": 500,
                "quantity_unit": "ml"
            },
            {
                "name": "water3",
                "quantity": 477,
                "quantity_unit": "ml"
            },
            {
                "name": "kimchi",
                "quantity": 359,
                "quantity_unit": "kg"
            }

        ]
    },
    {
        "name": "curry",
        "like": 5,
        "ings": [
            {
                "name": "red pepper",
                "quantity": 500,
                "quantity_unit": 50
            },
            {
                "name": "onion",
                "quantity": 700,
                "quantity_unit": "kg"
            },
            {
                "name": "kimchi",
                "quantity": 20,
                "quantity_unit": "kg"
            }
        ]
    }
]
